vantoanpackage/vantoan.py
vantoanpackage-1.0.0.dist-info/METADATA
vantoanpackage-1.0.0.dist-info/WHEEL
vantoanpackage-1.0.0.dist-info/RECORD
