Metadata-Version: 2.4
Name: vantoanpackage
Version: 1.0.0
Summary: Made by Vawn Toan
Author: Lee Vawn Toan
Requires-Python: >=3.11
Classifier: Programming Language :: Python :: 3
Classifier: Programming Language :: Python :: 3.11
Classifier: Programming Language :: Python :: 3.12
Classifier: Programming Language :: Python :: 3.13
Classifier: Programming Language :: Python :: 3.14
